[{"username":"fuck","password":"ab8f06ff1ccfd53986ffaf56dd02004d1fc61839069568b4b55598a25a5a4f10","nickname":"fuck","email":"fuck@email.com","slogan":"","passwordRecoveryQuestion":"What is my father\u0027s name?","passwordRecoveryAnswer":"fuck","highScore":0},{"username":"kasra","password":"00558ae83b574ad91e046d9ff2268ce1580c48d0c3ec06a53538dca1f6f59e62","nickname":"kasra","email":"kasra@email.com","slogan":"","passwordRecoveryQuestion":"What is my father\u0027s name?","passwordRecoveryAnswer":"kasra","highScore":0},{"username":"amir","password":"a8a46b2faf782a6373118dcb32119fd9bc96c132d6fe70d3a0950503a043f938","nickname":"amir","email":"amir@amir.com","slogan":"","passwordRecoveryQuestion":"What is my father\u0027s name?","passwordRecoveryAnswer":"amir","highScore":0}]